{"name":"WHAT A BUILDING APP","tagline":"Projecte del grup 101.1 de l'asignatura GDSA de la UPC. ","body":"![](C:\\Users\\Marc\\Downloads\\logo_WBapp.jpg)\r\nSom el **grup 101.1** de l'assignatura de GDSA (Gestió i Distribució de Senyals Audiovisuals), format per: \r\n* Albert Altarriba\r\n* Cristian Camps\r\n* Marc Lladó\r\n* Carlos Manso\r\n* Sergi Santana\r\n\r\n\r\n## UPC Terrassa \r\nEstudiants del grau en Enginyeria de Sistemes Audiovisuals a la Universitat Politècnica de Terrassa. \r\n\r\n### El Projecte\r\nEns pots seguir al nostre repositori:\r\n[Repositori del What a building App](https://github.com/gdsa-upc/What-a-building-App)\r\n\r\nAquí podeu trobar les presentacuions de cada setmana (Weekly report) per tal de fer el seguiment i veure com el projecte va avançant.\r\n* [Sessió 3](https://docs.google.com/presentation/d/1nhOBICOFf1w9uZaILL3p_XdLangvuzF6UWGSWky7ajw/edit#slide=id.ge8d7f0586_0_59)\r\n\r\n* [Sessió 4](https://docs.google.com/presentation/d/1eWARLhBUta1__Fkso_XZCJwunTnInZsQYMJ8I9ivgh8/edit?usp=sharing)\r\n\r\n* [Sessió 5](https://docs.google.com/presentation/d/1JrSL9gzmd6s7CqA5K-jkkBWopHPjLLEzCQIvW39O2io/edit?usp=sharing)\r\n\r\n\r\nRecentment hem dissenyat un logo que ens representi com a grup per tal de ser més visuals i capti l'atenció del públic.\r\n![](https://drive.google.com/file/d/0Bxh06U1B8SPhSFktV2NLVTY4T1U/view)\r\n\r\n![](blob:https%3A//drive.google.com/d7e09e8f-b4da-401e-9874-a20c813bb16b)\r\n>A nosaltres ens va tocar fer les fotografies a dos edificis emblemàtics de Terrassa, a més d'altres fotos de qualsevol edifici que seria calificat com a desconegut. Es repartirien així:\r\n* 50 fotos al **Mercat de la Independencia**\r\n* 50 fotos al Museu de la Ciència i la Tecnologia- **MNACTEC**\r\n* 50 fotos a altres edificis -->categoria **_desconeguts_**\r\n\r\n![](http://imagenes.forociudad.com/fotos/32481-terrassa-mercat-de-la-independencia.jpg)\r\n\r\n\r\n![](http://andrestecnoweb.com/img/1_energias/16654.src.jpg)\r\n\r\n>A la primera sessió a més de les fotogries, també vam crear el primer script del projecte. Aquest consistia en trobar els punts d'interès d'una imatge. L'objectiu del projecte és que quan consultem una imatge sobre un edifici, ens indiqui a quin  correspon i mostri una llista amb els que més s'hi assemblin. \r\n\r\n![](http://geospatialtraininges.com/wp-content/uploads/2013/07/python-logo-master.png)\r\n\r\n>Per desenvolupar el projecte, utilitzem l'editor Enthought Canopy i el llenguatge Python per programar. Llibreries com opencv i scikit-learn, entre d'altres, són utilitzades per dur a terme els nostres scripts.\r\n\r\n>","google":"","note":"Don't delete this file! It's used internally to help with page regeneration."}